.gitignore
CHANGES.txt
MANIFEST.in
README.rst
bootstrap.py
buildout.cfg
collective.linguasitemap-configure.zcml
jenkins.cfg
setup.py
collective/__init__.py
collective.linguasitemap.egg-info/PKG-INFO
collective.linguasitemap.egg-info/SOURCES.txt
collective.linguasitemap.egg-info/dependency_links.txt
collective.linguasitemap.egg-info/entry_points.txt
collective.linguasitemap.egg-info/namespace_packages.txt
collective.linguasitemap.egg-info/not-zip-safe
collective.linguasitemap.egg-info/requires.txt
collective.linguasitemap.egg-info/top_level.txt
collective/linguasitemap/__init__.py
collective/linguasitemap/configure.zcml
collective/linguasitemap/rebuild_i18n.sh
collective/linguasitemap/testing.py
collective/linguasitemap/browser/__init__.py
collective/linguasitemap/browser/configure.zcml
collective/linguasitemap/browser/interfaces.py
collective/linguasitemap/browser/sitemap.py
collective/linguasitemap/locales/collective.linguasitemap.pot
collective/linguasitemap/locales/en/LC_MESSAGES/collective.linguasitemap.po
collective/linguasitemap/locales/fr/LC_MESSAGES/collective.linguasitemap.po
collective/linguasitemap/profiles/default/browserlayer.xml
collective/linguasitemap/profiles/default/metadata.xml
collective/linguasitemap/tests/__init__.py
collective/linguasitemap/tests/base.py
collective/linguasitemap/tests/test_setup.py
collective/linguasitemap/tests/test_sitemap.py
collective/linguasitemap/tests/test_traverser.py
collective/linguasitemap/tests/utils.py
collective/linguasitemap/upgrades/__init__.py
collective/linguasitemap/upgrades/configure.zcml
collective/linguasitemap/upgrades/v1000_to_1001.py