Metadata-Version: 1.0
Name: collective.linguasitemap
Version: 1.0a2
Summary: Sitemap for MultiLanguage Plone site using LinguaPlone
Home-page: https://github.com/collective/collective.linguasitemap
Author: JeanMichel FRANCOIS aka toutpt
Author-email: toutpt@gmail.com
License: GPL
Keywords: plone multilanguage lingaplone sitemap
Platform: UNKNOWN
Classifier: Programming Language :: Python
Classifier: Framework :: Plone
Classifier: Framework :: Plone :: 4.0
Classifier: Framework :: Plone :: 4.1
Classifier: Framework :: Plone :: 4.2
